lazyk.cpython-313t-x86_64-linux-gnu.so
lazy_k-0.1.5.dist-info/METADATA
lazy_k-0.1.5.dist-info/WHEEL
lazy_k-0.1.5.dist-info/top_level.txt
lazy_k-0.1.5.dist-info/RECORD
lazy_k-0.1.5.dist-info/licenses/LICENSE
