Metadata-Version: 2.4
Name: lazy_k
Version: 0.1.5
Summary: A C++ implementation of the Lazy-k algorithm (A* with partial expansion)
Author-email: Arthur Hemmer <arthurhemmer@hotmail.com>
Project-URL: Homepage, https://github.com/arthurdevnl/lazyk
Classifier: Programming Language :: Python :: 3
Classifier: Operating System :: OS Independent
Requires-Python: >=3.10
License-File: LICENSE
Dynamic: license-file
Dynamic: requires-python
